rosetta_sip_factory/__init__.py
rosetta_sip_factory/sip_builder.py
rosetta_sip_factory-0.1.10.dist-info/LICENSE.txt
rosetta_sip_factory-0.1.10.dist-info/METADATA
rosetta_sip_factory-0.1.10.dist-info/WHEEL
rosetta_sip_factory-0.1.10.dist-info/top_level.txt
rosetta_sip_factory-0.1.10.dist-info/RECORD
